terra_fixt.py
pytest_terra_fixt-0.6.2.dist-info/LICENSE
pytest_terra_fixt-0.6.2.dist-info/METADATA
pytest_terra_fixt-0.6.2.dist-info/WHEEL
pytest_terra_fixt-0.6.2.dist-info/entry_points.txt
pytest_terra_fixt-0.6.2.dist-info/top_level.txt
pytest_terra_fixt-0.6.2.dist-info/RECORD
