Metadata-Version: 2.1
Name: pytest-terra-fixt
Version: 0.6.2
Summary: Terraform and Terragrunt fixtures for pytest
Home-page: https://github.com/marshall7m/pytest-terra-fixt
Author: Marshall Mamiya
Project-URL: Bug Tracker, https://github.com/marshall7m/pytest-terra-fixt/issues
Classifier: Programming Language :: Python :: 3
Classifier: License :: OSI Approved :: MIT License
Classifier: Operating System :: OS Independent
Classifier: Framework :: Pytest
License-File: LICENSE
Requires-Dist: pytest (==6.2.5)
Requires-Dist: tftest (==1.7.2)
Provides-Extra: testing
Requires-Dist: pytest (==6.2.5) ; extra == 'testing'
Requires-Dist: tftest (==1.7.2) ; extra == 'testing'
Requires-Dist: mock (==4.0.3) ; extra == 'testing'
Requires-Dist: pytest-mock (==3.6.1) ; extra == 'testing'
